consultify/__init__.py
consultify/consultify.py
consultify-0.0.2.4.dist-info/LICENSE
consultify-0.0.2.4.dist-info/METADATA
consultify-0.0.2.4.dist-info/WHEEL
consultify-0.0.2.4.dist-info/top_level.txt
consultify-0.0.2.4.dist-info/RECORD
