Metadata-Version: 2.1
Name: consultify
Version: 0.0.2.4
Summary: Turns analyses on Python into management consulting-style PowerPoint slides.
Home-page: https://github.com/ryancarlyu/consultify
Author: Ryan Yu
Author-email: ryu@mba2021.hbs.edu
License: UNKNOWN
Platform: UNKNOWN
Classifier: Programming Language :: Python :: 3
Classifier: License :: OSI Approved :: MIT License
Classifier: Operating System :: OS Independent
Requires-Dist: python-pptx
Requires-Dist: pandas
